gunther/__init__.py
gunther/beacon.py
gunther/ip.py
gunther/socket4.py
gunther/socket6.py
gunther/transport.py
gunther-2023.7.21.dist-info/METADATA
gunther-2023.7.21.dist-info/WHEEL
gunther-2023.7.21.dist-info/RECORD
